setup.py
PublicNotificationsPlugin.egg-info/PKG-INFO
PublicNotificationsPlugin.egg-info/SOURCES.txt
PublicNotificationsPlugin.egg-info/dependency_links.txt
PublicNotificationsPlugin.egg-info/entry_points.txt
PublicNotificationsPlugin.egg-info/not-zip-safe
PublicNotificationsPlugin.egg-info/top_level.txt
publicnotifications/__init__.py
publicnotifications/api.py