Metadata-Version: 1.0
Name: PublicNotificationsPlugin
Version: 0.1.2
Summary: Allow to define CC address(es) used only for public tickets notifications.
Home-page: http://mitar.tnode.com/
Author: Mitar
Author-email: mitar.trac@tnode.com
License: AGPLv3
Keywords: trac plugin
Platform: UNKNOWN
